orbqt/__init__.py
orbqt/__main__.py
orbqt/orbqt.py
orbqt/test_test.py
orbqt/3dQt_example/README.md
orbqt/3dQt_example/simpleQt3d.py
orbqt/3dQt_example/test.py
orbqt/system/__init__.py
orbqt/system/default_paths.py
orbqt/system/logging_configuration.py
orbqt-0.0.0.dist-info/entry_points.txt
orbqt-0.0.0.dist-info/LICENSE
orbqt-0.0.0.dist-info/WHEEL
orbqt-0.0.0.dist-info/METADATA
orbqt-0.0.0.dist-info/RECORD
